yaml_ld/__init__.py
yaml_ld/cli.py
yaml_ld/compact.py
yaml_ld/document_loaders/__init__.py
yaml_ld/document_loaders/base.py
yaml_ld/document_loaders/choice_by_scheme.py
yaml_ld/document_loaders/content_types.py
yaml_ld/document_loaders/default.py
yaml_ld/document_loaders/http.py
yaml_ld/document_loaders/local_file.py
yaml_ld/document_loaders/mock.py
yaml_ld/document_parsers/__init__.py
yaml_ld/document_parsers/base.py
yaml_ld/document_parsers/html_parser.py
yaml_ld/document_parsers/markdown_parser.py
yaml_ld/document_parsers/rdf_xml_parser.py
yaml_ld/document_parsers/turtle_parser.py
yaml_ld/document_parsers/yaml_parser.py
yaml_ld/errors.py
yaml_ld/expand.py
yaml_ld/flatten.py
yaml_ld/frame.py
yaml_ld/from_rdf.py
yaml_ld/load_document.py
yaml_ld/loader.py
yaml_ld/models.py
yaml_ld/options.py
yaml_ld/rdf.py
yaml_ld/string_as_url_or_path.py
yaml_ld/to_rdf.py
yaml_ld-1.1.16.dist-info/METADATA
yaml_ld-1.1.16.dist-info/WHEEL
yaml_ld-1.1.16.dist-info/entry_points.txt
yaml_ld-1.1.16.dist-info/RECORD
