Metadata-Version: 2.3
Name: yaml-ld
Version: 1.1.16
Summary: YAML-LD for Python
License: MIT
Author: Anatoly Scherbakov
Author-email: altaisoft@gmail.com
Requires-Python: >=3.10,<4.0
Classifier: License :: OSI Approved :: MIT License
Classifier: Programming Language :: Python :: 3
Classifier: Programming Language :: Python :: 3.10
Classifier: Programming Language :: Python :: 3.11
Classifier: Programming Language :: Python :: 3.12
Classifier: Programming Language :: Python :: 3.13
Requires-Dist: PyLD (>=2.0.4)
Requires-Dist: beautifulsoup4 (>=4.12.3)
Requires-Dist: documented (>=0.1.4)
Requires-Dist: funcy (>=2.0)
Requires-Dist: pydantic (>=2.7.4)
Requires-Dist: python-frontmatter (>=0.5.0)
Requires-Dist: pyyaml (>=6.0.1)
Requires-Dist: rdflib-pyld-compat (>=0.1.0)
Requires-Dist: requests-cache (>=1.2.1)
Requires-Dist: typer (>=0.15.1)
Requires-Dist: yarl (>=1.9.4)
